fastedit/__init__.py
fastedit/editor.py
fastedit/rome/__init__.py
fastedit/rome/compute_u.py
fastedit/rome/compute_v.py
fastedit/rome/repr_tools.py
fastedit/rome/rome_hparams.py
fastedit/rome/rome_main.py
fastedit/utils/__init__.py
fastedit/utils/context.py
fastedit/utils/generate.py
fastedit/utils/hparams.py
fastedit/utils/mtloader.py
fastedit/utils/nethook.py
fastedit/utils/prints.py
fastedit/utils/template.py
pyfastedit-0.0.5.dist-info/LICENSE
pyfastedit-0.0.5.dist-info/METADATA
pyfastedit-0.0.5.dist-info/WHEEL
pyfastedit-0.0.5.dist-info/top_level.txt
pyfastedit-0.0.5.dist-info/RECORD
