Metadata-Version: 2.1
Name: pyfastedit
Version: 0.0.5
Summary: Editing large language models within 10 seconds
Home-page: https://github.com/hiyouga/FastEdit
Author: hiyouga
Author-email: hiyouga@buaa.edu.cn
License: Apache 2.0 License
Keywords: LLM,ChatGPT,transformer,pytorch,deep learning
Classifier: Development Status :: 3 - Alpha
Classifier: Intended Audience :: Developers
Classifier: Intended Audience :: Education
Classifier: Intended Audience :: Science/Research
Classifier: License :: OSI Approved :: Apache Software License
Classifier: Operating System :: OS Independent
Classifier: Programming Language :: Python :: 3
Classifier: Programming Language :: Python :: 3.8
Classifier: Programming Language :: Python :: 3.9
Classifier: Programming Language :: Python :: 3.10
Classifier: Topic :: Scientific/Engineering :: Artificial Intelligence
Requires-Python: >=3.8.0
License-File: LICENSE
Requires-Dist: torch (>=1.13.1)
Requires-Dist: transformers (>=4.29.1)
Requires-Dist: datasets (>=2.12.0)
Requires-Dist: accelerate (>=0.19.0)
Requires-Dist: sentencepiece
Requires-Dist: fire
